db_hooks/__init__.py
db_hooks/__main__.py
db_hooks/cache.py
db_hooks/cli.py
db_hooks/client.py
db_hooks/config.py
db_hooks/editor.py
db_hooks/errors.py
db_hooks/password.py
db_hooks/sqlalchemy.py
db_hooks-0.4.0.dist-info/LICENSE
db_hooks-0.4.0.dist-info/METADATA
db_hooks-0.4.0.dist-info/NOTICE
db_hooks-0.4.0.dist-info/WHEEL
db_hooks-0.4.0.dist-info/entry_points.txt
db_hooks-0.4.0.dist-info/top_level.txt
db_hooks-0.4.0.dist-info/RECORD
