Metadata-Version: 2.1
Name: db-hooks
Version: 0.4.0
Summary: A simple sqlalchemy connection configuration manager
Home-page: https://github.com/jfhbrook/db_hooks
Author: Joshua Holbrook
Author-email: josh.holbrook@gmail.com
License: UNKNOWN
Keywords: sqlalchemy,repl,jupyter,database
Platform: UNKNOWN
Classifier: Programming Language :: Python
Classifier: Development Status :: 3 - Alpha
Classifier: Programming Language :: Python :: 3
Classifier: Topic :: Database
Classifier: Topic :: Database :: Front-Ends
Requires-Python: >=3.5
Requires-Dist: appdirs
Requires-Dist: attrs
Requires-Dist: cachetools
Requires-Dist: cattrs
Requires-Dist: click
Requires-Dist: click-log
Requires-Dist: pygments
Requires-Dist: sqlalchemy
Requires-Dist: toml
